yodf/__init__.py
yodf/core.py
yodf/operations.py
yodf/train.py
yodf-1.0.16.dist-info/WHEEL
yodf-1.0.16.dist-info/METADATA
yodf-1.0.16.dist-info/RECORD
