Metadata-Version: 2.1
Name: yodf
Version: 1.0.16
Summary: 'Hello, World!' Forward Mode Autdiff library with Tensorflow 1 like interface.
Home-page: https://github.com/yogimogi/yodf
Author: Yogesh Ketkar
Author-email: yogimogi@gmail.com
Requires-Python: >=3.6,<4.0
Classifier: Programming Language :: Python :: 3
Classifier: Programming Language :: Python :: 3.6
Classifier: Programming Language :: Python :: 3.7
Classifier: Programming Language :: Python :: 3.8
Classifier: Programming Language :: Python :: 3.9
Requires-Dist: numpy (>=1.19.4,<2.0.0)
Project-URL: Repository, https://github.com/yogimogi/yodf
